Workbook
Name _a1: #REF!
Name _a1: #REF!
Name AAVE: #REF!
Name AAVE: #REF!
Name APE: #REF!
Name APE: #REF!
Name AVAX: #REF!
Name AVAX: #REF!
Name Banks: #REF!
Name Banks: #REF!
Name BCH: #REF!
Name BCH: #REF!
Name BTC: #REF!
Name BTC: #REF!
Name CHZ: #REF!
Name CHZ: #REF!
Name COMPANY: #REF!
Name COMPANY: #REF!
Name CRV: #REF!
Name CRV: #REF!
Name Curr: #REF!
Name Curr: #REF!
Name Data1: #REF!,#REF!
Name Data1: #REF!,#REF!
Name dkk: #REF!
Name dkk: #REF!
Name DLTReturn_AvailableFunds: #REF!
Name DLTReturn_AvailableFunds: #REF!
Name DLTReturn_CapitalRequirement: #REF!
Name DLTReturn_CapitalRequirement: #REF!
Name DLTReturn_CashAtBankInHand: #REF!
Name DLTReturn_CashAtBankInHand: #REF!
Name DLTReturn_Inventories: #REF!
Name DLTReturn_Inventories: #REF!
Name DLTReturn_InvestmentsInSubs: #REF!
Name DLTReturn_InvestmentsInSubs: #REF!
Name DLTReturn_LegalFees: #REF!
Name DLTReturn_LegalFees: #REF!
Name DLTReturn_OfficeRent: #REF!
Name DLTReturn_OfficeRent: #REF!
Name DLTReturn_PrepaymentsAccruedIncome: #REF!
Name DLTReturn_PrepaymentsAccruedIncome: #REF!
Name DLTReturn_ReservesRevalFixAssets: #REF!
Name DLTReturn_ReservesRevalFixAssets: #REF!
Name DLTReturn_TangibleAssets: #REF!
Name DLTReturn_TangibleAssets: #REF!
Name DLTReturn_TradeDebtors: #REF!
Name DLTReturn_TradeDebtors: #REF!
Name DLTReturn_TransExRPCust: #REF!
Name DLTReturn_TransExRPCust: #REF!
Name DLTReturn_W1YAmtsGroupCosConnectedPers: #REF!
Name DLTReturn_W1YAmtsGroupCosConnectedPers: #REF!
Name DLTReturn_YTDProfit: #REF!
Name DLTReturn_YTDProfit: #REF!
Name DOGE: #REF!
Name DOGE: #REF!
Name DOT: #REF!
Name DOT: #REF!
Name EETH: #REF!
Name EETH: #REF!

Sheet Mappings - New
A1: Substrings | B1: R/D | C1: Consolidated Entity | D1: 13WCF Line Item Mapping
A2: Credit TRF | B2: Disbursement | C2: Bullish | D2: All Other
A3: Bullish SG Lunch Club | B3: Disbursement | C3: Bullish | D3: All Other
A4: Office Lunch | B4: Disbursement | C4: Bullish | D4: All Other
A5: Payroll | B5: Disbursement | C5: Bullish | D5: Staff & Bonus
A6: Payroll | B6: Disbursement | C6: CoinDesk | D6: Staff & Bonus
A7: HK Electric Co LTD | B7: Disbursement | C7: Bullish | D7: All Other
A8: CSL Mobile LTD | B8: Disbursement | C8: Bullish | D8: All Other
A9: CPF Board | B9: Receipt | C9: Bullish | D9: Rewards and Other Interest
A10: Ministry of Manpower | B10: Disbursement | C10: Bullish | D10: All Other
A11: HSBCNet Monthly Fee | B11: Disbursement | C11: Bullish | D11: All Other
A12: Income Tax | B12: Disbursement | C12: Bullish | D12: Tax Payments
... A186: HIDDENROADPARTNE | B186: Receipt | C186: Bullish | D186: Rewards and Other Interest

Sheet 13WCF Categories
A1: OpEx Specific Categories
A2: Staff & Bonus
A3: Cloud, IT & Software
A4: Consulting, Contracting, Prof Fees
A5: Legal Fees
A6: Advertising, Promotion & Production
A7: Liquidity Routing Funding
A8: Additional Perp Funding
A9: Tax Payments
A10: Facilities Rent
A11: All Other

Sheet Entity_Supplier_13WCF_Mapping
A1: Bullish Ledger Accounts | B1: Bullish Group Hierarchy | C1: 13WCF Mapped Entity | D1: Supplier | E1: Spend Category | F1: 13WCF Mapping
A2: 602002:Audit Fees | B2: Bullish Global | C2: =INDEX('[1]Entity and 13WCF Line Mapping'!C:C,MATCH(Entity_Supplier_13WCF_Mapping!B2,'[1]Entity and 13WCF Line Mapping'!B:B,0)) -> Bullish Global | D2: Deloitte & Touche LLP | E2: Audit Fees | F2: Consulting, Contracting, Prof Fees
A3: 607300:Contractors | B3: CoinDesk, Inc. | C3: =INDEX('[1]Entity and 13WCF Line Mapping'!C:C,MATCH(Entity_Supplier_13WCF_Mapping!B3,'[1]Entity and 13WCF Line Mapping'!B:B,0)) -> CoinDesk | D3: Akshit Walian | E3: Independent Contractor | F3: Consulting, Contracting, Prof Fees
A4: 602000:Professional Fees | B4: Bullish Global | C4: =INDEX('[1]Entity and 13WCF Line Mapping'!C:C,MATCH(Entity_Supplier_13WCF_Mapping!B4,'[1]Entity and 13WCF Line Mapping'!B:B,0)) -> Bullish Global | D4: Digital Asset Services Ltd | E4: Professional Service Fees | F4: Consulting, Contracting, Prof Fees
A5: 470000:Net Foreign Exchange (Gains)/Losses | B5: CoinDesk, Inc. | C5: =INDEX('[1]Entity and 13WCF Line Mapping'!C:C,MATCH(Entity_Supplier_13WCF_Mapping!B5,'[1]Entity and 13WCF Line Mapping'!B:B,0)) -> CoinDesk | D5: The Cool Designs Limited | E5: Bank FX gain/(loss) | F5: All Other
A6: 607300:Contractors | B6: CoinDesk, Inc. | C6: =INDEX('[1]Entity and 13WCF Line Mapping'!C:C,MATCH(Entity_Supplier_13WCF_Mapping!B6,'[1]Entity and 13WCF Line Mapping'!B:B,0)) -> CoinDesk | D6: Jeffrey Wilser | E6: Freelancers | F6: Staff & Bonus
A7: 603001:Cloud Services | B7: CoinDesk, Inc. | C7: =INDEX('[1]Entity and 13WCF Line Mapping'!C:C,MATCH(Entity_Supplier_13WCF_Mapping!B7,'[1]Entity and 13WCF Line Mapping'!B:B,0)) -> CoinDesk | D7: Vercel | E7: Cloud Services | F7: Cloud, IT & Software
A8: 600000:Advertising & Promotion | B8: CoinDesk, Inc. | C8: =INDEX('[1]Entity and 13WCF Line Mapping'!C:C,MATCH(Entity_Supplier_13WCF_Mapping!B8,'[1]Entity and 13WCF Line Mapping'!B:B,0)) -> CoinDesk | D8: Brave Software International | E8: MarComm Paid Media | F8: All Other
A9: 602000:Professional Fees | B9: Bullish (GI) Limited | C9: =INDEX('[1]Entity and 13WCF Line Mapping'!C:C,MATCH(Entity_Supplier_13WCF_Mapping!B9,'[1]Entity and 13WCF Line Mapping'!B:B,0)) -> Bullish (GI) Limited | D9: BCB Payments (Europe) SASU | E9: Professional Service Fees | F9: Consulting, Contracting, Prof Fees
A10: 603001:Cloud Services | B10: Bullish Global | C10: =INDEX('[1]Entity and 13WCF Line Mapping'!C:C,MATCH(Entity_Supplier_13WCF_Mapping!B10,'[1]Entity and 13WCF Line Mapping'!B:B,0)) -> Bullish Global | D10: TreasuryGO, Inc | E10: Cloud Services | F10: Cloud, IT & Software
A11: 602000:Professional Fees | B11: Bullish Global | C11: =INDEX('[1]Entity and 13WCF Line Mapping'!C:C,MATCH(Entity_Supplier_13WCF_Mapping!B11,'[1]Entity and 13WCF Line Mapping'!B:B,0)) -> Bullish Global | D11: Acclime Singapore Pte. Ltd | E11: Professional Service Fees | F11: Consulting, Contracting, Prof Fees
A12: 651000:Depreciation Property, Plant & Equipment | B12: Bullish (GI) Limited | C12: =INDEX('[1]Entity and 13WCF Line Mapping'!C:C,MATCH(Entity_Supplier_13WCF_Mapping!B12,'[1]Entity and 13WCF Line Mapping'!B:B,0)) -> Bullish (GI) Limited | D12: Ocean Village Commercial Properties Ltd | E12: Right of use asset | F12: All Other
A13: 470000:Net Foreign Exchange (Gains)/Losses | B13: CoinDesk, Inc. | C13: =INDEX('[1]Entity and 13WCF Line Mapping'!C:C,MATCH(Entity_Supplier_13WCF_Mapping!B13,'[1]Entity and 13WCF Line Mapping'!B:B,0)) -> CoinDesk | D13: Zenno Group Limited | E13: Realized FX gain/(loss) | F13: All Other
... A1513: 600000:Advertising & Promotion | B1513: CoinDesk, Inc. | C1513: =INDEX('[1]Entity and 13WCF Line Mapping'!C:C,MATCH(Entity_Supplier_13WCF_Mapping!B1513,'[1]Entity and 13WCF Line Mapping'!B:B,0)) -> CoinDesk | D1513: Digital Business Lab | E1513: MarComm KOLs | F1513: All Other
B1514: Bullish DE Custody GmbH (USD) | C1514: =INDEX('[1]Entity and 13WCF Line Mapping'!C:C,MATCH(Entity_Supplier_13WCF_Mapping!B1514,'[1]Entity and 13WCF Line Mapping'!B:B,0)) -> Bullish DE Custody GmbH | D1514: Blitzstart Services GmbH | F1514: Consulting, Contracting, Prof Fees
